{
  "id": "conversa1",
  "nome": "Conversa de Jantar",
  "categoria": "social",
  "tags": [
    "comida",
    "jantar",
    "japones"
  ],
  "participantesMinimos": 2,
  "participantesMaximos": 2,
  "duracaoEstimada": "10-15 minutos",
  "mensagens": [
    {
      "ordem": 1,
      "remetente": 0,
      "texto": "Você topa comer japonês hoje?",
      "delay": {
        "min": 2,
        "max": 5
      },
      "comportamento": {
        "marcarComoLida": true,
        "tempoAntesLeitura": {
          "min": 1,
          "max": 3
        },
        "simularDigitacao": true,
        "tempoDigitacao": {
          "min": 2,
          "max": 4
        }
      }
    },
    {
      "ordem": 2,
      "remetente": 1,
      "texto": "Topo demais! Faz tempo que não como sushi 🍣",
      "delay": {
        "min": 3,
        "max": 6
      },
      "comportamento": {
        "marcarComoLida": true,
        "tempoAntesLeitura": {
          "min": 1,
          "max": 2
        },
        "simularDigitacao": true,
        "tempoDigitacao": {
          "min": 3,
          "max": 5
        }
      }
    },
    {
      "ordem": 3,
      "remetente": 0,
      "texto": "Prefere rodízio ou pedir delivery?",
      "delay": {
        "min": 2,
        "max": 4
      },
      "comportamento": {
        "marcarComoLida": true,
        "tempoAntesLeitura": {
          "min": 1,
          "max": 2
        },
        "simularDigitacao": true,
        "tempoDigitacao": {
          "min": 2,
          "max": 4
        }
      }
    },
    {
      "ordem": 4,
      "remetente": 1,
      "texto": "Acho que delivery hoje é melhor, tô cansado 😅",
      "delay": {
        "min": 2,
        "max": 5
      },
      "comportamento": {
        "marcarComoLida": true,
        "tempoAntesLeitura": {
          "min": 1,
          "max": 3
        },
        "simularDigitacao": true,
        "tempoDigitacao": {
          "min": 2,
          "max": 5
        }
      }
    },
    {
      "ordem": 5,
      "tipo": "pausa_longa",
      "duracao": {
        "min": 120,
        "max": 240
      }
    },
    {
      "ordem": 6,
      "remetente": 0,
      "texto": "Beleza! Vou pedir um combinado grande então.",
      "delay": {
        "min": 3,
        "max": 6
      },
      "comportamento": {
        "marcarComoLida": true,
        "tempoAntesLeitura": {
          "min": 1,
          "max": 2
        },
        "simularDigitacao": true,
        "tempoDigitacao": {
          "min": 3,
          "max": 5
        }
      }
    },
    {
      "ordem": 7,
      "remetente": 1,
      "texto": "Boa! Pede também hot roll e guioza 😍",
      "delay": {
        "min": 2,
        "max": 5
      },
      "comportamento": {
        "marcarComoLida": true,
        "tempoAntesLeitura": {
          "min": 1,
          "max": 2
        },
        "simularDigitacao": true,
        "tempoDigitacao": {
          "min": 2,
          "max": 4
        }
      }
    },
    {
      "ordem": 8,
      "remetente": 0,
      "texto": "Fechado! Já tô até com fome agora 😂",
      "delay": {
        "min": 2,
        "max": 4
      },
      "comportamento": {
        "marcarComoLida": true,
        "tempoAntesLeitura": {
          "min": 1,
          "max": 2
        },
        "simularDigitacao": true,
        "tempoDigitacao": {
          "min": 2,
          "max": 3
        }
      }
    }
  ],
  "metadados": {
    "criadaPor": "sistema",
    "vezesUsada": 0,
    "ultimoUso": null,
    "efetividade": null
  }
}