{
  "id": "conv_auto_010",
  "nome": "Conversa 10",
  "categoria": "cotidiano",
  "tags": [
    "chat",
    "conversa"
  ],
  "participantesMinimos": 2,
  "participantesMaximos": 2,
  "duracaoEstimada": "10-60 minutos",
  "mensagens": [
    {
      "ordem": 1,
      "remetente": 0,
      "texto": "MATURADOR_APAGAR oi sumida! o que vai fazer sabado?",
      "delay": {
        "min": 20,
        "max": 30
      },
      "comportamento": {
        "marcarComoLida": true,
        "tempoAntesLeitura": {
          "min": 15,
          "max": 20
        },
        "simularDigitacao": true,
        "tempoDigitacao": {
          "min": 30,
          "max": 40
        }
      }
    },
    {
      "ordem": 2,
      "remetente": 1,
      "texto": "MATURADOR_APAGAR oi! pensei em ir na praia, vem?",
      "delay": {
        "min": 20,
        "max": 30
      },
      "comportamento": {
        "marcarComoLida": true,
        "tempoAntesLeitura": {
          "min": 15,
          "max": 20
        },
        "simularDigitacao": true,
        "tempoDigitacao": {
          "min": 30,
          "max": 40
        }
      }
    },
    {
      "ordem": 3,
      "remetente": 1,
      "texto": "MATURADOR_APAGAR adorei! que horas?",
      "delay": {
        "min": 20,
        "max": 30
      },
      "comportamento": {
        "marcarComoLida": true,
        "tempoAntesLeitura": {
          "min": 15,
          "max": 20
        },
        "simularDigitacao": true,
        "tempoDigitacao": {
          "min": 30,
          "max": 40
        }
      }
    },
    {
      "ordem": 4,
      "remetente": 0,
      "texto": "MATURADOR_APAGAR 9h antes de lotar",
      "delay": {
        "min": 20,
        "max": 30
      },
      "comportamento": {
        "marcarComoLida": true,
        "tempoAntesLeitura": {
          "min": 15,
          "max": 20
        },
        "simularDigitacao": true,
        "tempoDigitacao": {
          "min": 30,
          "max": 40
        }
      }
    },
    {
      "ordem": 5,
      "remetente": 0,
      "texto": "MATURADOR_APAGAR perfeito, vai ter mais gente?",
      "delay": {
        "min": 20,
        "max": 30
      },
      "comportamento": {
        "marcarComoLida": true,
        "tempoAntesLeitura": {
          "min": 15,
          "max": 20
        },
        "simularDigitacao": true,
        "tempoDigitacao": {
          "min": 30,
          "max": 40
        }
      }
    },
    {
      "ordem": 6,
      "remetente": 1,
      "texto": "MATURADOR_APAGAR o Renan e a Jess tb vao",
      "delay": {
        "min": 20,
        "max": 30
      },
      "comportamento": {
        "marcarComoLida": true,
        "tempoAntesLeitura": {
          "min": 15,
          "max": 20
        },
        "simularDigitacao": true,
        "tempoDigitacao": {
          "min": 30,
          "max": 40
        }
      }
    },
    {
      "ordem": 7,
      "remetente": 0,
      "texto": "MATURADOR_APAGAR que bom faz tempo que nao os vejo",
      "delay": {
        "min": 20,
        "max": 30
      },
      "comportamento": {
        "marcarComoLida": true,
        "tempoAntesLeitura": {
          "min": 15,
          "max": 20
        },
        "simularDigitacao": true,
        "tempoDigitacao": {
          "min": 30,
          "max": 40
        }
      }
    },
    {
      "ordem": 8,
      "remetente": 1,
      "texto": "MATURADOR_APAGAR vai ser otimo mesmo",
      "delay": {
        "min": 20,
        "max": 30
      },
      "comportamento": {
        "marcarComoLida": true,
        "tempoAntesLeitura": {
          "min": 15,
          "max": 20
        },
        "simularDigitacao": true,
        "tempoDigitacao": {
          "min": 30,
          "max": 40
        }
      }
    },
    {
      "ordem": 9,
      "remetente": 1,
      "texto": "MATURADOR_APAGAR levo o cooler?",
      "delay": {
        "min": 20,
        "max": 30
      },
      "comportamento": {
        "marcarComoLida": true,
        "tempoAntesLeitura": {
          "min": 15,
          "max": 20
        },
        "simularDigitacao": true,
        "tempoDigitacao": {
          "min": 30,
          "max": 40
        }
      }
    },
    {
      "ordem": 10,
      "tipo": "pausa_longa",
      "duracao": {
        "min": 62,
        "max": 374
      }
    },
    {
      "ordem": 11,
      "remetente": 0,
      "texto": "MATURADOR_APAGAR leva sim eu levo as cadeiras",
      "delay": {
        "min": 20,
        "max": 30
      },
      "comportamento": {
        "marcarComoLida": true,
        "tempoAntesLeitura": {
          "min": 15,
          "max": 20
        },
        "simularDigitacao": true,
        "tempoDigitacao": {
          "min": 30,
          "max": 40
        }
      }
    },
    {
      "ordem": 12,
      "remetente": 1,
      "texto": "MATURADOR_APAGAR combina, precisa levar comida?",
      "delay": {
        "min": 20,
        "max": 30
      },
      "comportamento": {
        "marcarComoLida": true,
        "tempoAntesLeitura": {
          "min": 15,
          "max": 20
        },
        "simularDigitacao": true,
        "tempoDigitacao": {
          "min": 30,
          "max": 40
        }
      }
    },
    {
      "ordem": 13,
      "tipo": "pausa_longa",
      "duracao": {
        "min": 101,
        "max": 316
      }
    },
    {
      "ordem": 14,
      "remetente": 0,
      "texto": "MATURADOR_APAGAR compra la mesmo",
      "delay": {
        "min": 20,
        "max": 30
      },
      "comportamento": {
        "marcarComoLida": true,
        "tempoAntesLeitura": {
          "min": 15,
          "max": 20
        },
        "simularDigitacao": true,
        "tempoDigitacao": {
          "min": 30,
          "max": 40
        }
      }
    },
    {
      "ordem": 15,
      "remetente": 0,
      "texto": "MATURADOR_APAGAR tem aquele espetinho do cara do chapeu",
      "delay": {
        "min": 20,
        "max": 30
      },
      "comportamento": {
        "marcarComoLida": true,
        "tempoAntesLeitura": {
          "min": 15,
          "max": 20
        },
        "simularDigitacao": true,
        "tempoDigitacao": {
          "min": 30,
          "max": 40
        }
      }
    },
    {
      "ordem": 16,
      "remetente": 1,
      "texto": "MATURADOR_APAGAR mesmo kkkk ja to com fome",
      "delay": {
        "min": 20,
        "max": 30
      },
      "comportamento": {
        "marcarComoLida": true,
        "tempoAntesLeitura": {
          "min": 15,
          "max": 20
        },
        "simularDigitacao": true,
        "tempoDigitacao": {
          "min": 30,
          "max": 40
        }
      }
    },
    {
      "ordem": 17,
      "tipo": "pausa_longa",
      "duracao": {
        "min": 150,
        "max": 431
      }
    },
    {
      "ordem": 18,
      "remetente": 0,
      "texto": "MATURADOR_APAGAR kkkk ainda ta quinta",
      "delay": {
        "min": 20,
        "max": 30
      },
      "comportamento": {
        "marcarComoLida": true,
        "tempoAntesLeitura": {
          "min": 15,
          "max": 20
        },
        "simularDigitacao": true,
        "tempoDigitacao": {
          "min": 30,
          "max": 40
        }
      }
    },
    {
      "ordem": 19,
      "remetente": 1,
      "texto": "MATURADOR_APAGAR to ansiosa demais",
      "delay": {
        "min": 20,
        "max": 30
      },
      "comportamento": {
        "marcarComoLida": true,
        "tempoAntesLeitura": {
          "min": 15,
          "max": 20
        },
        "simularDigitacao": true,
        "tempoDigitacao": {
          "min": 30,
          "max": 40
        }
      }
    },
    {
      "ordem": 20,
      "remetente": 0,
      "texto": "MATURADOR_APAGAR vou dormir cedo sexta",
      "delay": {
        "min": 20,
        "max": 30
      },
      "comportamento": {
        "marcarComoLida": true,
        "tempoAntesLeitura": {
          "min": 15,
          "max": 20
        },
        "simularDigitacao": true,
        "tempoDigitacao": {
          "min": 30,
          "max": 40
        }
      }
    },
    {
      "ordem": 21,
      "remetente": 1,
      "texto": "MATURADOR_APAGAR boa ideia, vai descansar",
      "delay": {
        "min": 20,
        "max": 30
      },
      "comportamento": {
        "marcarComoLida": true,
        "tempoAntesLeitura": {
          "min": 15,
          "max": 20
        },
        "simularDigitacao": true,
        "tempoDigitacao": {
          "min": 30,
          "max": 40
        }
      }
    },
    {
      "ordem": 22,
      "remetente": 0,
      "texto": "MATURADOR_APAGAR combinado! qq coisa me avisa",
      "delay": {
        "min": 20,
        "max": 30
      },
      "comportamento": {
        "marcarComoLida": true,
        "tempoAntesLeitura": {
          "min": 15,
          "max": 20
        },
        "simularDigitacao": true,
        "tempoDigitacao": {
          "min": 30,
          "max": 40
        }
      }
    },
    {
      "ordem": 23,
      "remetente": 1,
      "texto": "MATURADOR_APAGAR aviso sim vai ser otimo",
      "delay": {
        "min": 20,
        "max": 30
      },
      "comportamento": {
        "marcarComoLida": true,
        "tempoAntesLeitura": {
          "min": 15,
          "max": 20
        },
        "simularDigitacao": true,
        "tempoDigitacao": {
          "min": 30,
          "max": 40
        }
      }
    },
    {
      "ordem": 24,
      "remetente": 0,
      "texto": "MATURADOR_APAGAR oi sumida! o que vai fazer sabado?",
      "delay": {
        "min": 20,
        "max": 30
      },
      "comportamento": {
        "marcarComoLida": true,
        "tempoAntesLeitura": {
          "min": 15,
          "max": 20
        },
        "simularDigitacao": true,
        "tempoDigitacao": {
          "min": 30,
          "max": 40
        }
      }
    },
    {
      "ordem": 25,
      "remetente": 1,
      "texto": "MATURADOR_APAGAR oi! pensei em ir na praia, vem?",
      "delay": {
        "min": 20,
        "max": 30
      },
      "comportamento": {
        "marcarComoLida": true,
        "tempoAntesLeitura": {
          "min": 15,
          "max": 20
        },
        "simularDigitacao": true,
        "tempoDigitacao": {
          "min": 30,
          "max": 40
        }
      }
    },
    {
      "ordem": 26,
      "remetente": 0,
      "texto": "MATURADOR_APAGAR adorei! que horas?",
      "delay": {
        "min": 20,
        "max": 30
      },
      "comportamento": {
        "marcarComoLida": true,
        "tempoAntesLeitura": {
          "min": 15,
          "max": 20
        },
        "simularDigitacao": true,
        "tempoDigitacao": {
          "min": 30,
          "max": 40
        }
      }
    },
    {
      "ordem": 27,
      "remetente": 0,
      "texto": "MATURADOR_APAGAR 9h antes de lotar",
      "delay": {
        "min": 20,
        "max": 30
      },
      "comportamento": {
        "marcarComoLida": true,
        "tempoAntesLeitura": {
          "min": 15,
          "max": 20
        },
        "simularDigitacao": true,
        "tempoDigitacao": {
          "min": 30,
          "max": 40
        }
      }
    },
    {
      "ordem": 28,
      "tipo": "pausa_longa",
      "duracao": {
        "min": 152,
        "max": 204
      }
    },
    {
      "ordem": 29,
      "remetente": 1,
      "texto": "MATURADOR_APAGAR perfeito, vai ter mais gente?",
      "delay": {
        "min": 20,
        "max": 30
      },
      "comportamento": {
        "marcarComoLida": true,
        "tempoAntesLeitura": {
          "min": 15,
          "max": 20
        },
        "simularDigitacao": true,
        "tempoDigitacao": {
          "min": 30,
          "max": 40
        }
      }
    },
    {
      "ordem": 30,
      "remetente": 0,
      "texto": "MATURADOR_APAGAR o Renan e a Jess tb vao",
      "delay": {
        "min": 20,
        "max": 30
      },
      "comportamento": {
        "marcarComoLida": true,
        "tempoAntesLeitura": {
          "min": 15,
          "max": 20
        },
        "simularDigitacao": true,
        "tempoDigitacao": {
          "min": 30,
          "max": 40
        }
      }
    },
    {
      "ordem": 31,
      "remetente": 1,
      "texto": "MATURADOR_APAGAR que bom faz tempo que nao os vejo",
      "delay": {
        "min": 20,
        "max": 30
      },
      "comportamento": {
        "marcarComoLida": true,
        "tempoAntesLeitura": {
          "min": 15,
          "max": 20
        },
        "simularDigitacao": true,
        "tempoDigitacao": {
          "min": 30,
          "max": 40
        }
      }
    },
    {
      "ordem": 32,
      "remetente": 0,
      "texto": "MATURADOR_APAGAR vai ser otimo mesmo",
      "delay": {
        "min": 20,
        "max": 30
      },
      "comportamento": {
        "marcarComoLida": true,
        "tempoAntesLeitura": {
          "min": 15,
          "max": 20
        },
        "simularDigitacao": true,
        "tempoDigitacao": {
          "min": 30,
          "max": 40
        }
      }
    },
    {
      "ordem": 33,
      "remetente": 1,
      "texto": "MATURADOR_APAGAR levo o cooler?",
      "delay": {
        "min": 20,
        "max": 30
      },
      "comportamento": {
        "marcarComoLida": true,
        "tempoAntesLeitura": {
          "min": 15,
          "max": 20
        },
        "simularDigitacao": true,
        "tempoDigitacao": {
          "min": 30,
          "max": 40
        }
      }
    },
    {
      "ordem": 34,
      "tipo": "pausa_longa",
      "duracao": {
        "min": 112,
        "max": 450
      }
    },
    {
      "ordem": 35,
      "remetente": 0,
      "texto": "MATURADOR_APAGAR leva sim eu levo as cadeiras",
      "delay": {
        "min": 20,
        "max": 30
      },
      "comportamento": {
        "marcarComoLida": true,
        "tempoAntesLeitura": {
          "min": 15,
          "max": 20
        },
        "simularDigitacao": true,
        "tempoDigitacao": {
          "min": 30,
          "max": 40
        }
      }
    },
    {
      "ordem": 36,
      "remetente": 1,
      "texto": "MATURADOR_APAGAR combina, precisa levar comida?",
      "delay": {
        "min": 20,
        "max": 30
      },
      "comportamento": {
        "marcarComoLida": true,
        "tempoAntesLeitura": {
          "min": 15,
          "max": 20
        },
        "simularDigitacao": true,
        "tempoDigitacao": {
          "min": 30,
          "max": 40
        }
      }
    },
    {
      "ordem": 37,
      "remetente": 0,
      "texto": "MATURADOR_APAGAR compra la mesmo",
      "delay": {
        "min": 20,
        "max": 30
      },
      "comportamento": {
        "marcarComoLida": true,
        "tempoAntesLeitura": {
          "min": 15,
          "max": 20
        },
        "simularDigitacao": true,
        "tempoDigitacao": {
          "min": 30,
          "max": 40
        }
      }
    },
    {
      "ordem": 38,
      "remetente": 1,
      "texto": "MATURADOR_APAGAR tem aquele espetinho do cara do chapeu",
      "delay": {
        "min": 20,
        "max": 30
      },
      "comportamento": {
        "marcarComoLida": true,
        "tempoAntesLeitura": {
          "min": 15,
          "max": 20
        },
        "simularDigitacao": true,
        "tempoDigitacao": {
          "min": 30,
          "max": 40
        }
      }
    },
    {
      "ordem": 39,
      "remetente": 1,
      "texto": "MATURADOR_APAGAR mesmo kkkk ja to com fome",
      "delay": {
        "min": 20,
        "max": 30
      },
      "comportamento": {
        "marcarComoLida": true,
        "tempoAntesLeitura": {
          "min": 15,
          "max": 20
        },
        "simularDigitacao": true,
        "tempoDigitacao": {
          "min": 30,
          "max": 40
        }
      }
    },
    {
      "ordem": 40,
      "remetente": 0,
      "texto": "MATURADOR_APAGAR kkkk ainda ta quinta",
      "delay": {
        "min": 20,
        "max": 30
      },
      "comportamento": {
        "marcarComoLida": true,
        "tempoAntesLeitura": {
          "min": 15,
          "max": 20
        },
        "simularDigitacao": true,
        "tempoDigitacao": {
          "min": 30,
          "max": 40
        }
      }
    },
    {
      "ordem": 41,
      "remetente": 1,
      "texto": "MATURADOR_APAGAR to ansiosa demais",
      "delay": {
        "min": 20,
        "max": 30
      },
      "comportamento": {
        "marcarComoLida": true,
        "tempoAntesLeitura": {
          "min": 15,
          "max": 20
        },
        "simularDigitacao": true,
        "tempoDigitacao": {
          "min": 30,
          "max": 40
        }
      }
    },
    {
      "ordem": 42,
      "remetente": 0,
      "texto": "MATURADOR_APAGAR vou dormir cedo sexta",
      "delay": {
        "min": 20,
        "max": 30
      },
      "comportamento": {
        "marcarComoLida": true,
        "tempoAntesLeitura": {
          "min": 15,
          "max": 20
        },
        "simularDigitacao": true,
        "tempoDigitacao": {
          "min": 30,
          "max": 40
        }
      }
    },
    {
      "ordem": 43,
      "remetente": 1,
      "texto": "MATURADOR_APAGAR boa ideia, vai descansar",
      "delay": {
        "min": 20,
        "max": 30
      },
      "comportamento": {
        "marcarComoLida": true,
        "tempoAntesLeitura": {
          "min": 15,
          "max": 20
        },
        "simularDigitacao": true,
        "tempoDigitacao": {
          "min": 30,
          "max": 40
        }
      }
    },
    {
      "ordem": 44,
      "remetente": 0,
      "texto": "MATURADOR_APAGAR combinado! qq coisa me avisa",
      "delay": {
        "min": 20,
        "max": 30
      },
      "comportamento": {
        "marcarComoLida": true,
        "tempoAntesLeitura": {
          "min": 15,
          "max": 20
        },
        "simularDigitacao": true,
        "tempoDigitacao": {
          "min": 30,
          "max": 40
        }
      }
    },
    {
      "ordem": 45,
      "remetente": 0,
      "texto": "MATURADOR_APAGAR aviso sim vai ser otimo",
      "delay": {
        "min": 20,
        "max": 30
      },
      "comportamento": {
        "marcarComoLida": true,
        "tempoAntesLeitura": {
          "min": 15,
          "max": 20
        },
        "simularDigitacao": true,
        "tempoDigitacao": {
          "min": 30,
          "max": 40
        }
      }
    },
    {
      "ordem": 46,
      "remetente": 1,
      "texto": "MATURADOR_APAGAR oi sumida! o que vai fazer sabado?",
      "delay": {
        "min": 20,
        "max": 30
      },
      "comportamento": {
        "marcarComoLida": true,
        "tempoAntesLeitura": {
          "min": 15,
          "max": 20
        },
        "simularDigitacao": true,
        "tempoDigitacao": {
          "min": 30,
          "max": 40
        }
      }
    },
    {
      "ordem": 47,
      "remetente": 0,
      "texto": "MATURADOR_APAGAR oi! pensei em ir na praia, vem?",
      "delay": {
        "min": 20,
        "max": 30
      },
      "comportamento": {
        "marcarComoLida": true,
        "tempoAntesLeitura": {
          "min": 15,
          "max": 20
        },
        "simularDigitacao": true,
        "tempoDigitacao": {
          "min": 30,
          "max": 40
        }
      }
    },
    {
      "ordem": 48,
      "tipo": "pausa_longa",
      "duracao": {
        "min": 112,
        "max": 377
      }
    },
    {
      "ordem": 49,
      "remetente": 1,
      "texto": "MATURADOR_APAGAR adorei! que horas?",
      "delay": {
        "min": 20,
        "max": 30
      },
      "comportamento": {
        "marcarComoLida": true,
        "tempoAntesLeitura": {
          "min": 15,
          "max": 20
        },
        "simularDigitacao": true,
        "tempoDigitacao": {
          "min": 30,
          "max": 40
        }
      }
    }
  ]
}