{
  "id": "conv_auto_035",
  "nome": "Conversa 35",
  "categoria": "trabalho",
  "tags": [
    "chat",
    "conversa"
  ],
  "participantesMinimos": 2,
  "participantesMaximos": 2,
  "duracaoEstimada": "10-60 minutos",
  "mensagens": [
    {
      "ordem": 1,
      "remetente": 0,
      "texto": "MATURADOR_APAGAR cara me chama na sala agora",
      "delay": {
        "min": 20,
        "max": 30
      },
      "comportamento": {
        "marcarComoLida": true,
        "tempoAntesLeitura": {
          "min": 15,
          "max": 20
        },
        "simularDigitacao": true,
        "tempoDigitacao": {
          "min": 30,
          "max": 40
        }
      }
    },
    {
      "ordem": 2,
      "remetente": 1,
      "texto": "MATURADOR_APAGAR o que foi??",
      "delay": {
        "min": 20,
        "max": 30
      },
      "comportamento": {
        "marcarComoLida": true,
        "tempoAntesLeitura": {
          "min": 15,
          "max": 20
        },
        "simularDigitacao": true,
        "tempoDigitacao": {
          "min": 30,
          "max": 40
        }
      }
    },
    {
      "ordem": 3,
      "remetente": 1,
      "texto": "MATURADOR_APAGAR vem aqui primeiro",
      "delay": {
        "min": 20,
        "max": 30
      },
      "comportamento": {
        "marcarComoLida": true,
        "tempoAntesLeitura": {
          "min": 15,
          "max": 20
        },
        "simularDigitacao": true,
        "tempoDigitacao": {
          "min": 30,
          "max": 40
        }
      }
    },
    {
      "ordem": 4,
      "tipo": "pausa_longa",
      "duracao": {
        "min": 116,
        "max": 369
      }
    },
    {
      "ordem": 5,
      "remetente": 0,
      "texto": "MATURADOR_APAGAR fui la... cara que noticia",
      "delay": {
        "min": 20,
        "max": 30
      },
      "comportamento": {
        "marcarComoLida": true,
        "tempoAntesLeitura": {
          "min": 15,
          "max": 20
        },
        "simularDigitacao": true,
        "tempoDigitacao": {
          "min": 30,
          "max": 40
        }
      }
    },
    {
      "ordem": 6,
      "remetente": 0,
      "texto": "MATURADOR_APAGAR e na melhor hora",
      "delay": {
        "min": 20,
        "max": 30
      },
      "comportamento": {
        "marcarComoLida": true,
        "tempoAntesLeitura": {
          "min": 15,
          "max": 20
        },
        "simularDigitacao": true,
        "tempoDigitacao": {
          "min": 30,
          "max": 40
        }
      }
    },
    {
      "ordem": 7,
      "tipo": "pausa_longa",
      "duracao": {
        "min": 110,
        "max": 222
      }
    },
    {
      "ordem": 8,
      "remetente": 1,
      "texto": "MATURADOR_APAGAR minha mulher vai ficar louca de felicidade",
      "delay": {
        "min": 20,
        "max": 30
      },
      "comportamento": {
        "marcarComoLida": true,
        "tempoAntesLeitura": {
          "min": 15,
          "max": 20
        },
        "simularDigitacao": true,
        "tempoDigitacao": {
          "min": 30,
          "max": 40
        }
      }
    },
    {
      "ordem": 9,
      "remetente": 1,
      "texto": "MATURADOR_APAGAR voce merece mano, trabalhou demais",
      "delay": {
        "min": 20,
        "max": 30
      },
      "comportamento": {
        "marcarComoLida": true,
        "tempoAntesLeitura": {
          "min": 15,
          "max": 20
        },
        "simularDigitacao": true,
        "tempoDigitacao": {
          "min": 30,
          "max": 40
        }
      }
    },
    {
      "ordem": 10,
      "remetente": 1,
      "texto": "MATURADOR_APAGAR obrigado de verdade",
      "delay": {
        "min": 20,
        "max": 30
      },
      "comportamento": {
        "marcarComoLida": true,
        "tempoAntesLeitura": {
          "min": 15,
          "max": 20
        },
        "simularDigitacao": true,
        "tempoDigitacao": {
          "min": 30,
          "max": 40
        }
      }
    },
    {
      "ordem": 11,
      "tipo": "pausa_longa",
      "duracao": {
        "min": 171,
        "max": 500
      }
    },
    {
      "ordem": 12,
      "remetente": 0,
      "texto": "MATURADOR_APAGAR aumento bom?",
      "delay": {
        "min": 20,
        "max": 30
      },
      "comportamento": {
        "marcarComoLida": true,
        "tempoAntesLeitura": {
          "min": 15,
          "max": 20
        },
        "simularDigitacao": true,
        "tempoDigitacao": {
          "min": 30,
          "max": 40
        }
      }
    },
    {
      "ordem": 13,
      "remetente": 1,
      "texto": "MATURADOR_APAGAR 20%",
      "delay": {
        "min": 20,
        "max": 30
      },
      "comportamento": {
        "marcarComoLida": true,
        "tempoAntesLeitura": {
          "min": 15,
          "max": 20
        },
        "simularDigitacao": true,
        "tempoDigitacao": {
          "min": 30,
          "max": 40
        }
      }
    },
    {
      "ordem": 14,
      "remetente": 1,
      "texto": "MATURADOR_APAGAR otimo! comemora essa noite",
      "delay": {
        "min": 20,
        "max": 30
      },
      "comportamento": {
        "marcarComoLida": true,
        "tempoAntesLeitura": {
          "min": 15,
          "max": 20
        },
        "simularDigitacao": true,
        "tempoDigitacao": {
          "min": 30,
          "max": 40
        }
      }
    },
    {
      "ordem": 15,
      "remetente": 1,
      "texto": "MATURADOR_APAGAR vou levar ela num jantar",
      "delay": {
        "min": 20,
        "max": 30
      },
      "comportamento": {
        "marcarComoLida": true,
        "tempoAntesLeitura": {
          "min": 15,
          "max": 20
        },
        "simularDigitacao": true,
        "tempoDigitacao": {
          "min": 30,
          "max": 40
        }
      }
    },
    {
      "ordem": 16,
      "remetente": 0,
      "texto": "MATURADOR_APAGAR restaurante bom, voce merece",
      "delay": {
        "min": 20,
        "max": 30
      },
      "comportamento": {
        "marcarComoLida": true,
        "tempoAntesLeitura": {
          "min": 15,
          "max": 20
        },
        "simularDigitacao": true,
        "tempoDigitacao": {
          "min": 30,
          "max": 40
        }
      }
    },
    {
      "ordem": 17,
      "remetente": 1,
      "texto": "MATURADOR_APAGAR qual vc indica?",
      "delay": {
        "min": 20,
        "max": 30
      },
      "comportamento": {
        "marcarComoLida": true,
        "tempoAntesLeitura": {
          "min": 15,
          "max": 20
        },
        "simularDigitacao": true,
        "tempoDigitacao": {
          "min": 30,
          "max": 40
        }
      }
    },
    {
      "ordem": 18,
      "remetente": 0,
      "texto": "MATURADOR_APAGAR tem um italiano novo na vila que e muito bom",
      "delay": {
        "min": 20,
        "max": 30
      },
      "comportamento": {
        "marcarComoLida": true,
        "tempoAntesLeitura": {
          "min": 15,
          "max": 20
        },
        "simularDigitacao": true,
        "tempoDigitacao": {
          "min": 30,
          "max": 40
        }
      }
    },
    {
      "ordem": 19,
      "remetente": 1,
      "texto": "MATURADOR_APAGAR manda o nome",
      "delay": {
        "min": 20,
        "max": 30
      },
      "comportamento": {
        "marcarComoLida": true,
        "tempoAntesLeitura": {
          "min": 15,
          "max": 20
        },
        "simularDigitacao": true,
        "tempoDigitacao": {
          "min": 30,
          "max": 40
        }
      }
    }
  ]
}